MANIFEST.in
setup.py
docs/CONTRIBUTORS.txt
docs/HISTORY.txt
docs/LICENSE.ZPL
docs/LICENSE.txt
docs/README.txt
src/ztfy/__init__.py
src/ztfy.sequence.egg-info/PKG-INFO
src/ztfy.sequence.egg-info/SOURCES.txt
src/ztfy.sequence.egg-info/dependency_links.txt
src/ztfy.sequence.egg-info/namespace_packages.txt
src/ztfy.sequence.egg-info/not-zip-safe
src/ztfy.sequence.egg-info/requires.txt
src/ztfy.sequence.egg-info/top_level.txt
src/ztfy/sequence/__init__.py
src/ztfy/sequence/adapter.py
src/ztfy/sequence/browser.py
src/ztfy/sequence/configure.zcml
src/ztfy/sequence/interfaces.py
src/ztfy/sequence/utility.py
src/ztfy/sequence/doctests/README.txt
src/ztfy/sequence/locales/ztfy.sequence.pot
src/ztfy/sequence/locales/en/LC_MESSAGES/ztfy.sequence.mo
src/ztfy/sequence/locales/en/LC_MESSAGES/ztfy.sequence.po
src/ztfy/sequence/locales/fr/LC_MESSAGES/ztfy.sequence.mo
src/ztfy/sequence/locales/fr/LC_MESSAGES/ztfy.sequence.po
src/ztfy/sequence/tal/__init__.py
src/ztfy/sequence/tal/api.py
src/ztfy/sequence/tal/configure.zcml
src/ztfy/sequence/tal/interfaces.py
src/ztfy/sequence/tests/__init__.py
src/ztfy/sequence/tests/test_docs.py
src/ztfy/sequence/tests/test_docstrings.py