Metadata-Version: 1.1
Name: ztfy.sequence
Version: 0.1.1
Summary: ZTFY utility used to generate sequences
Home-page: http://www.ztfy.org
Author: Thierry Florac
Author-email: tflorac@ulthar.net
License: ZPL
Platform: UNKNOWN
Classifier: Programming Language :: Python
